cartographer/__init__.py
cartographer/model.py
cartographer/model_viz.py
cartographer/model_viz_demo.py
cartographer/reference_model.py
cartographer/test_model.py
naive_cartographer-3.0.1.dist-info/METADATA
naive_cartographer-3.0.1.dist-info/WHEEL
naive_cartographer-3.0.1.dist-info/RECORD
