Metadata-Version: 2.4
Name: naive-cartographer
Version: 3.0.1
Summary: A naive Bayes Markov decision process learner
Project-URL: Documentation, https://codeberg.org/brohrer/cartographer-paper/raw/branch/main/cartographer.pdf
Project-URL: README, https://codeberg.org/brohrer/cartographer/src/branch/main/README.md
Project-URL: Repository, https://codeberg.org/brohrer/cartographer.git
Author-email: Brandon Rohrer <brohrer@gmail.com>
Classifier: License :: OSI Approved :: MIT License
Classifier: Operating System :: OS Independent
Classifier: Programming Language :: Python :: 3
Requires-Python: >=3.12
Requires-Dist: matplotlib
Requires-Dist: numba
Requires-Dist: numpy
